SetPrecision/SetPrecision.py
SetPrecision/__init__.py
SetPrecision/tests/SetPrecision_test.py
SetPrecision/tests/__init__.py
SetPrecision-0.2.0.dist-info/LICENSE
SetPrecision-0.2.0.dist-info/METADATA
SetPrecision-0.2.0.dist-info/WHEEL
SetPrecision-0.2.0.dist-info/top_level.txt
SetPrecision-0.2.0.dist-info/RECORD
