Metadata-Version: 2.1
Name: SetPrecision
Version: 0.2.0
Summary: Python module providing an easy way to set the precision of a floating-point number/decimal to the desired amount of significant figures.
Home-page: https://github.com/schlopp96/SetPrecision
Author: schlopp96
Author-email: schloppdaddy@gmail.com
License: UNKNOWN
Keywords: SetPrecision,float,decimal,precision,sig,figs,significant,digits,scientific,notation,math,conversion,script,point,floating,scientific-notation
Platform: UNKNOWN
Classifier: Development Status :: 3 - Alpha
Classifier: Intended Audience :: Developers
Classifier: Intended Audience :: End Users/Desktop
Classifier: License :: OSI Approved :: GNU General Public License v3 (GPLv3)
Classifier: Natural Language :: English
Classifier: Operating System :: Microsoft :: Windows
Classifier: Programming Language :: Python :: 3
Classifier: Programming Language :: Python :: 3.9
Classifier: Programming Language :: Python :: 3.10
Classifier: Topic :: Software Development :: Libraries :: Python Modules
Classifier: Topic :: Scientific/Engineering :: Mathematics
Classifier: Topic :: Utilities
License-File: LICENSE
Requires-Dist: setuptools (>=58.1.0)
